turkanime_api/__init__.py
turkanime_api/bypass.py
turkanime_api/cli/__main__.py
turkanime_api/cli/cli_tools.py
turkanime_api/cli/dosyalar.py
turkanime_api/cli/gereksinimler.py
turkanime_api/cli/version.py
turkanime_api/objects.py
turkanime_cli-9.0.0.dist-info/entry_points.txt
turkanime_cli-9.0.0.dist-info/LICENSE
turkanime_cli-9.0.0.dist-info/METADATA
turkanime_cli-9.0.0.dist-info/WHEEL
turkanime_cli-9.0.0.dist-info/RECORD
