Metadata-Version: 2.3
Name: turkanime-cli
Version: 9.0.0
Summary: Türkanime video oynatıcı ve indirici
License: CC-BY-NC-ND-4.0
Keywords: turkanime,turk,anime,downloader
Author: Junicchi
Author-email: junicchi@waifu.club
Requires-Python: >=3.9,<4
Classifier: Environment :: Console
Classifier: License :: Other/Proprietary License
Classifier: Programming Language :: Python :: 3
Classifier: Programming Language :: Python :: 3.9
Classifier: Programming Language :: Python :: 3.10
Classifier: Programming Language :: Python :: 3.11
Classifier: Programming Language :: Python :: 3.12
Classifier: Programming Language :: Python :: 3.13
Requires-Dist: appdirs
Requires-Dist: curl-cffi (>=0.13)
Requires-Dist: easygui (>=0.98.2)
Requires-Dist: py7zr
Requires-Dist: pycryptodome
Requires-Dist: questionary
Requires-Dist: rich (>=13.0.0)
Requires-Dist: yt-dlp[curl-cffi,default]
Project-URL: Repository, https://github.com/kebablord/turkanime-indirici
